rudolph/__init__.py
rudolph/api.py
rudolph/utils.py
rudolph/model/__init__.py
rudolph/model/fp16.py
rudolph/model/image_attention.py
rudolph/model/model.py
rudolph/model/transformer.py
rudolph/model/utils.py
rudolph-0.0.1rc10.dist-info/LICENSE.txt
rudolph-0.0.1rc10.dist-info/METADATA
rudolph-0.0.1rc10.dist-info/WHEEL
rudolph-0.0.1rc10.dist-info/top_level.txt
rudolph-0.0.1rc10.dist-info/RECORD
