Metadata-Version: 2.1
Name: rudolph
Version: 0.0.1rc10
Summary: RuDOLPH: One Hyper-Modal Transformer can be creative as DALL-E and smart as CLIP
Author: SberAI, SberDevices
Author-email: shonenkov@phystech.edu
License-File: LICENSE.txt
Requires-Dist: rudalle (==1.1.3)
Requires-Dist: taming-transformers (==0.0.1)
Requires-Dist: more-itertools (>=8.10.0)
Requires-Dist: transformers (~=4.10.2)
Requires-Dist: youtokentome (>=1.0.6)
Requires-Dist: omegaconf (>=2.0.0)
Requires-Dist: einops (~=0.3.2)
Requires-Dist: torch
Requires-Dist: torchvision
Requires-Dist: matplotlib
